dimo_sdk-0.0.3.data/data/requirements.txt
hub/__init__.py
hub/client.py
test/__init__.py
test/client.py
test/usage.py
dimo_sdk-0.0.3.dist-info/METADATA
dimo_sdk-0.0.3.dist-info/WHEEL
dimo_sdk-0.0.3.dist-info/top_level.txt
dimo_sdk-0.0.3.dist-info/RECORD
