Metadata-Version: 2.1
Name: dimo-sdk
Version: 0.0.3
Summary: dimo sdk
Home-page: https://pypi.org/project/dimo-sdk/
Author: moss
Author-email: yydfjt@gmail.com
Classifier: Programming Language :: Python :: 3
Classifier: License :: OSI Approved :: MIT License
Classifier: Operating System :: OS Independent
Requires-Python: >=3.6
Requires-Dist: requests
